setup.py
simind/__init__.py
simind/index_classes.py
simind.egg-info/PKG-INFO
simind.egg-info/SOURCES.txt
simind.egg-info/dependency_links.txt
simind.egg-info/not-zip-safe
simind.egg-info/requires.txt
simind.egg-info/top_level.txt
test/test.py