Metadata-Version: 1.0
Name: simind
Version: 0.0.2
Summary: Compute various incidence based or abundance based similarity indices between two numpy arrays.
Home-page: https://github.com/benmaier/similarity-indices
Author: Benjamin F. Maier
Author-email: benjaminfrankmaier@gmail.com
License: MIT
Platform: UNKNOWN
